{
    "configurations": [
        {
            "name": "linux",
            "includePath": [
                "c/inc",
                "c/stm32f3/cmsis/inc",
                "c/stm32f3/hal/inc",
                "c/usb_vcp/inc"
            ],
            "defines": [
                "STM32F3",
                "STM32F303xC",
                "HAL_PCD_MODULE_ENABLED",
                "SENSOR=6050",
                "DSHOT=1",
                "ONESHOT=0",
                "ESC=1",
                "DHSOT_RATE=600",
                "BEEPER",
                "VBAT",
                "IBAT",
                "OSD",
                "RUNCAM",
                "SMART_AUDIO",
                "LED"
            ],
            "intelliSenseMode": "gcc-arm",
            "compilerPath": "/tools/gcc-arm-none-eabi-10.3-2021.10/bin/arm-none-eabi-gcc",
            "cStandard": "c11",
            "cppStandard": "gnu++14"
        }
    ],
    "version": 4
}